neatnearestneighbour/__init__.py
neatnearestneighbour/distance.py
neatnearestneighbour/nearestneighbour.py
neatnearestneighbour-1.0.0.dist-info/LICENSE
neatnearestneighbour-1.0.0.dist-info/METADATA
neatnearestneighbour-1.0.0.dist-info/WHEEL
neatnearestneighbour-1.0.0.dist-info/top_level.txt
neatnearestneighbour-1.0.0.dist-info/RECORD
