Metadata-Version: 2.1
Name: neatnearestneighbour
Version: 1.0.0
Summary: A nearest neighbour algorithm written in pure Python.
Home-page: https://gitlab.com/landreville/neatnearestneighbour
Author: Landreville
License: UNKNOWN
Platform: UNKNOWN
Classifier: Programming Language :: Python
Classifier: Programming Language :: Python :: 3
Classifier: Programming Language :: Python :: Implementation :: PyPy
Classifier: License :: OSI Approved :: GNU Affero General Public License v3
